ConvertingNS.py
convertingns-1.0.0.dist-info/WHEEL
convertingns-1.0.0.dist-info/METADATA
convertingns-1.0.0.dist-info/RECORD
